planqk/qiskit/__init__.py
planqk/quantum/sdk/__init__.py
planqk/quantum/sdk/_version.py
planqk/quantum/sdk/backend.py
planqk/quantum/sdk/context.py
planqk/quantum/sdk/credentials.py
planqk/quantum/sdk/decorators.py
planqk/quantum/sdk/exceptions.py
planqk/quantum/sdk/job.py
planqk/quantum/sdk/braket/__init__.py
planqk/quantum/sdk/braket/aws_device.py
planqk/quantum/sdk/braket/aws_dm1_device.py
planqk/quantum/sdk/braket/aws_sv1_device.py
planqk/quantum/sdk/braket/braket_provider.py
planqk/quantum/sdk/braket/gate_based_device.py
planqk/quantum/sdk/braket/ionq_aria_device.py
planqk/quantum/sdk/braket/iqm_garnet_device.py
planqk/quantum/sdk/braket/planqk_quantum_task.py
planqk/quantum/sdk/braket/quera_aquila_device.py
planqk/quantum/sdk/braket/rigetti_ankaa_device.py
planqk/quantum/sdk/client/__init__.py
planqk/quantum/sdk/client/backend_dtos.py
planqk/quantum/sdk/client/backend_factory.py
planqk/quantum/sdk/client/client.py
planqk/quantum/sdk/client/dto_utils.py
planqk/quantum/sdk/client/job_dtos.py
planqk/quantum/sdk/client/model_enums.py
planqk/quantum/sdk/client/session_dtos.py
planqk/quantum/sdk/qiskit/__init__.py
planqk/quantum/sdk/qiskit/backend.py
planqk/quantum/sdk/qiskit/job.py
planqk/quantum/sdk/qiskit/job_factory.py
planqk/quantum/sdk/qiskit/options.py
planqk/quantum/sdk/qiskit/planqk_qiskit_runtime_job.py
planqk/quantum/sdk/qiskit/planqk_qiskit_runtime_service.py
planqk/quantum/sdk/qiskit/provider.py
planqk/quantum/sdk/qiskit/providers/__init__.py
planqk/quantum/sdk/qiskit/providers/aws/__init__.py
planqk/quantum/sdk/qiskit/providers/aws/aws_backend.py
planqk/quantum/sdk/qiskit/providers/aws/aws_iqm_garnet_backend.py
planqk/quantum/sdk/qiskit/providers/aws/aws_qiskit_job.py
planqk/quantum/sdk/qiskit/providers/aws/aws_rigetti_ankaa_backend.py
planqk/quantum/sdk/qiskit/providers/azure/__init__.py
planqk/quantum/sdk/qiskit/providers/azure/azure_backend.py
planqk/quantum/sdk/qiskit/providers/azure/azure_qiskit_job.py
planqk_quantum-2.28.0.dist-info/licenses/LICENSE
planqk_quantum-2.28.0.dist-info/METADATA
planqk_quantum-2.28.0.dist-info/WHEEL
planqk_quantum-2.28.0.dist-info/entry_points.txt
planqk_quantum-2.28.0.dist-info/top_level.txt
planqk_quantum-2.28.0.dist-info/RECORD
