Metadata-Version: 2.4
Name: planqk-quantum
Version: 2.28.0
Summary: SDK to interact with PLANQK quantum backends.
Author-email: Kipu Quantum GmbH <info@kipu-quantum.com>
Maintainer-email: Sebastian Wagner <sebastian.wagner@kipu-quantum.com>, Michael Wurster <michael.wurster@kipu-quantum.com>
License:                                  Apache License
Project-URL: Homepage, https://kipu-quantum.com/platform
Project-URL: Documentation, https://docs.planqk.de
Project-URL: Repository, https://gitlab.com/planqk-foss/planqk-quantum
Project-URL: Issues, https://gitlab.com/planqk-foss/planqk-quantum/-/issues
Project-URL: Changelog, https://gitlab.com/planqk-foss/planqk-quantum/-/blob/main/CHANGELOG.md
Classifier: Programming Language :: Python :: 3
Classifier: License :: OSI Approved :: Apache Software License
Classifier: Operating System :: OS Independent
Requires-Python: >=3.11
License-File: LICENSE
Requires-Dist: pydantic<2.11.0,>=2.5.0
Requires-Dist: qiskit==1.4.5
Requires-Dist: qiskit-braket-provider==0.9.0
Requires-Dist: qiskit-ibm-runtime==0.43.1
Requires-Dist: qiskit-ionq==0.6.1
Requires-Dist: requests>=2.32.4
Requires-Dist: numba>=0.60.0
Dynamic: license-file
